{"feed":{"author":{"name":{"label":"iTunes Store"}, "uri":{"label":"http://www.apple.com/itunes/"}}, "entry":[
{"im:name":{"label":"BIG MONEY STYLIST"}, "im:image":[
{"label":"https://is3-ssl.mzstatic.com/image/thumb/Podcasts128/v4/f7/73/91/f77391bf-d13c-62c7-185f-4e16b9c72e58/mza_7344449501495592047.png/55x55bb-85.png", "attributes":{"height":"55"}}, 
{"label":"https://is4-ssl.mzstatic.com/image/thumb/Podcasts128/v4/f7/73/91/f77391bf-d13c-62c7-185f-4e16b9c72e58/mza_7344449501495592047.png/60x60bb-85.png", "attributes":{"height":"60"}}, 
{"label":"https://is1-ssl.mzstatic.com/image/thumb/Podcasts128/v4/f7/73/91/f77391bf-d13c-62c7-185f-4e16b9c72e58/mza_7344449501495592047.png/170x170bb-85.png", "attributes":{"height":"170"}}], "summary":{"label":"Danielle K White, owner of DKW Styling and creator of Natural Beaded Rows (NBR) had a vision as a hair stylist to bring value and purpose to others through hair extensions, taking this industry to an even greater level with Lead Stylists Valerie Plunk and Anianne Rivera, merging their elite skills as Artists with the business aspect of being a Salon Owner with Danielle’s husband, Garrett J White, founder of Wake Up Warrior and co-owner of DKW Styling."}, "im:price":{"label":"Get", "attributes":{"amount":"0", "currency":"USD"}}, "im:contentType":{"attributes":{"term":"Podcast", "label":"Podcast"}}, "rights":{"label":"© WARRIOR EMPIRE"}, "title":{"label":"BIG MONEY STYLIST - WARRIOR EMPIRE"}, "link":{"attributes":{"rel":"alternate", "type":"text/html", "href":"https://itunes.apple.com/us/podcast/big-money-stylist/id1332221101?mt=2&uo=2"}}, "id":{"label":"https://itunes.apple.com/us/podcast/big-money-stylist/id1332221101?mt=2&uo=2", "attributes":{"im:id":"1332221101"}}, "im:artist":{"label":"WARRIOR EMPIRE", "attributes":{"href":"https://itunes.apple.com/us/artist/warrior-empire/962205851?mt=2&uo=2"}}, "category":{"attributes":{"im:id":"1459", "term":"Fashion & Beauty", "scheme":"https://itunes.apple.com/us/genre/podcasts-arts-fashion-beauty/id1459?mt=2&uo=2", "label":"Fashion & Beauty"}}, "im:releaseDate":{"label":"2018-06-12T03:00:00-07:00", "attributes":{"label":"June 12, 2018"}}}, 
{"im:name":{"label":"Hairbrained Conversations"}, "im:price":{"label":"Get", "attributes":{"amount":"0", "currency":"USD"}}, "im:image":[
{"label":"https://is2-ssl.mzstatic.com/image/thumb/Podcasts122/v4/9f/bf/a2/9fbfa28a-6b6f-c34d-05ac-be8e85012cc1/mza_5425319499555416308.jpg/55x55bb-85.png", "attributes":{"height":"55"}}, 
{"label":"https://is3-ssl.mzstatic.com/image/thumb/Podcasts122/v4/9f/bf/a2/9fbfa28a-6b6f-c34d-05ac-be8e85012cc1/mza_5425319499555416308.jpg/60x60bb-85.png", "attributes":{"height":"60"}}, 
{"label":"https://is5-ssl.mzstatic.com/image/thumb/Podcasts122/v4/9f/bf/a2/9fbfa28a-6b6f-c34d-05ac-be8e85012cc1/mza_5425319499555416308.jpg/170x170bb-85.png", "attributes":{"height":"170"}}], "summary":{"label":"A weekly podcast that takes a deep dive into the minds of some of the most talented artists, educators, influencers, and leaders in the professional salon industry.  Hosted by Gordon Miller, Hairbrained.me ceo and self-proclaimed social media evangelist."}, "im:artist":{"label":"Hairbrained"}, "title":{"label":"Hairbrained Conversations - Hairbrained"}, "link":{"attributes":{"rel":"alternate", "type":"text/html", "href":"https://itunes.apple.com/us/podcast/hairbrained-conversations/id1319419913?mt=2&uo=2"}}, "id":{"label":"https://itunes.apple.com/us/podcast/hairbrained-conversations/id1319419913?mt=2&uo=2", "attributes":{"im:id":"1319419913"}}, "im:contentType":{"attributes":{"term":"Podcast", "label":"Podcast"}}, "category":{"attributes":{"im:id":"1459", "term":"Fashion & Beauty", "scheme":"https://itunes.apple.com/us/genre/podcasts-arts-fashion-beauty/id1459?mt=2&uo=2", "label":"Fashion & Beauty"}}, "im:releaseDate":{"label":"2018-06-17T00:00:00-07:00", "attributes":{"label":"June 17, 2018"}}}, 
{"im:name":{"label":"Fashion No Filter"}, "im:image":[
{"label":"https://is2-ssl.mzstatic.com/image/thumb/Podcasts111/v4/64/14/c0/6414c0d1-8906-05f8-90ba-50237e39cd7e/mza_1961445143560647500.png/55x55bb-85.png", "attributes":{"height":"55"}}, 
{"label":"https://is3-ssl.mzstatic.com/image/thumb/Podcasts111/v4/64/14/c0/6414c0d1-8906-05f8-90ba-50237e39cd7e/mza_1961445143560647500.png/60x60bb-85.png", "attributes":{"height":"60"}}, 
{"label":"https://is3-ssl.mzstatic.com/image/thumb/Podcasts111/v4/64/14/c0/6414c0d1-8906-05f8-90ba-50237e39cd7e/mza_1961445143560647500.png/170x170bb-85.png", "attributes":{"height":"170"}}], "summary":{"label":"Fashion journalists Camille Charriere and Monica Ainley give you a unique, behind the scenes look at how the fashion industry operates."}, "im:price":{"label":"Get", "attributes":{"amount":"0", "currency":"USD"}}, "im:contentType":{"attributes":{"term":"Podcast", "label":"Podcast"}}, "rights":{"label":"© SamFry Limited 2017"}, "title":{"label":"Fashion No Filter - SamFry Limited"}, "link":{"attributes":{"rel":"alternate", "type":"text/html", "href":"https://itunes.apple.com/us/podcast/fashion-no-filter/id1183345770?mt=2&uo=2"}}, "id":{"label":"https://itunes.apple.com/us/podcast/fashion-no-filter/id1183345770?mt=2&uo=2", "attributes":{"im:id":"1183345770"}}, "im:artist":{"label":"SamFry Limited"}, "category":{"attributes":{"im:id":"1459", "term":"Fashion & Beauty", "scheme":"https://itunes.apple.com/us/genre/podcasts-arts-fashion-beauty/id1459?mt=2&uo=2", "label":"Fashion & Beauty"}}, "im:releaseDate":{"label":"2018-03-02T10:36:00-07:00", "attributes":{"label":"March 2, 2018"}}}, 
{"im:name":{"label":"Breaking Beauty Podcast"}, "im:image":[
{"label":"https://is2-ssl.mzstatic.com/image/thumb/Podcasts115/v4/c9/56/04/c95604b1-2514-1a83-fdf2-4e219f4b53db/mza_8901214094458671886.jpg/55x55bb-85.png", "attributes":{"height":"55"}}, 
{"label":"https://is3-ssl.mzstatic.com/image/thumb/Podcasts115/v4/c9/56/04/c95604b1-2514-1a83-fdf2-4e219f4b53db/mza_8901214094458671886.jpg/60x60bb-85.png", "attributes":{"height":"60"}}, 
{"label":"https://is2-ssl.mzstatic.com/image/thumb/Podcasts115/v4/c9/56/04/c95604b1-2514-1a83-fdf2-4e219f4b53db/mza_8901214094458671886.jpg/170x170bb-85.png", "attributes":{"height":"170"}}], "summary":{"label":"Behind every bestselling beauty product, there's a damn good story. Two longtime magazine beauty editors, Jill Dunn and Carlene Higgins, chat about the breakthrough beauty products lining store shelves, and how they came to be. Each month, we talk to the industry’s most genius founders, and find out how they broke into the biz, with a little beauty idea that blew up into a million-dollar success story. Find out which products beauty editors and insiders really hoard, while hearing the struggles and successes behind the world's buzziest beauty brands. Plus, check out their mid-month episodes where they give hot takes on the latest launches and reviews!"}, "im:price":{"label":"Get", "attributes":{"amount":"0", "currency":"USD"}}, "im:contentType":{"attributes":{"term":"Podcast", "label":"Podcast"}}, "rights":{"label":"© All rights reserved"}, "title":{"label":"Breaking Beauty Podcast - Jill Dunn and Carlene Higgins"}, "link":{"attributes":{"rel":"alternate", "type":"text/html", "href":"https://itunes.apple.com/us/podcast/breaking-beauty-podcast/id1214452771?mt=2&uo=2"}}, "id":{"label":"https://itunes.apple.com/us/podcast/breaking-beauty-podcast/id1214452771?mt=2&uo=2", "attributes":{"im:id":"1214452771"}}, "im:artist":{"label":"Jill Dunn and Carlene Higgins"}, "category":{"attributes":{"im:id":"1459", "term":"Fashion & Beauty", "scheme":"https://itunes.apple.com/us/genre/podcasts-arts-fashion-beauty/id1459?mt=2&uo=2", "label":"Fashion & Beauty"}}, "im:releaseDate":{"label":"2018-06-13T03:30:00-07:00", "attributes":{"label":"June 13, 2018"}}}, 
{"im:name":{"label":"Pod Save The Queen"}, "im:price":{"label":"Get", "attributes":{"amount":"0", "currency":"USD"}}, "im:image":[
{"label":"https://is5-ssl.mzstatic.com/image/thumb/Podcasts128/v4/f7/67/f4/f767f449-9dea-78d3-394b-08f0c3454655/mza_2911779173759315584.png/55x55bb-85.png", "attributes":{"height":"55"}}, 
{"label":"https://is1-ssl.mzstatic.com/image/thumb/Podcasts128/v4/f7/67/f4/f767f449-9dea-78d3-394b-08f0c3454655/mza_2911779173759315584.png/60x60bb-85.png", "attributes":{"height":"60"}}, 
{"label":"https://is1-ssl.mzstatic.com/image/thumb/Podcasts128/v4/f7/67/f4/f767f449-9dea-78d3-394b-08f0c3454655/mza_2911779173759315584.png/170x170bb-85.png", "attributes":{"height":"170"}}], "summary":{"label":"All the excitement of Prince Harry and Meghan Markle's royal wedding, the new royal baby and a time of transition for the royal family, brought to you by Daily Mirror royal correspondent Victoria Murphy and host Ann Gripper."}, "im:artist":{"label":"Daily Mirror"}, "title":{"label":"Pod Save The Queen - Daily Mirror"}, "link":{"attributes":{"rel":"alternate", "type":"text/html", "href":"https://itunes.apple.com/us/podcast/pod-save-the-queen/id1326865967?mt=2&uo=2"}}, "id":{"label":"https://itunes.apple.com/us/podcast/pod-save-the-queen/id1326865967?mt=2&uo=2", "attributes":{"im:id":"1326865967"}}, "im:contentType":{"attributes":{"term":"Podcast", "label":"Podcast"}}, "category":{"attributes":{"im:id":"1459", "term":"Fashion & Beauty", "scheme":"https://itunes.apple.com/us/genre/podcasts-arts-fashion-beauty/id1459?mt=2&uo=2", "label":"Fashion & Beauty"}}, "im:releaseDate":{"label":"2018-06-12T12:12:00-07:00", "attributes":{"label":"June 12, 2018"}}}, 
{"im:name":{"label":"Outfit"}, "im:image":[
{"label":"https://is2-ssl.mzstatic.com/image/thumb/Podcasts115/v4/16/4f/95/164f9560-2e9f-a008-828b-ce93766459cf/mza_4674980979773466196.png/55x55bb-85.png", "attributes":{"height":"55"}}, 
{"label":"https://is3-ssl.mzstatic.com/image/thumb/Podcasts115/v4/16/4f/95/164f9560-2e9f-a008-828b-ce93766459cf/mza_4674980979773466196.png/60x60bb-85.png", "attributes":{"height":"60"}}, 
{"label":"https://is5-ssl.mzstatic.com/image/thumb/Podcasts115/v4/16/4f/95/164f9560-2e9f-a008-828b-ce93766459cf/mza_4674980979773466196.png/170x170bb-85.png", "attributes":{"height":"170"}}], "summary":{"label":"A queer fashion podcast exploring the relationship between gender, presentation, sexuality, and our wardrobes. Hosted by Ellen Ford, featuring high profile guests like queer fashion designers, a fashion psychologist, and her dad."}, "im:price":{"label":"Get", "attributes":{"amount":"0", "currency":"USD"}}, "im:contentType":{"attributes":{"term":"Podcast", "label":"Podcast"}}, "rights":{"label":"© Copyright 2018 All rights reserved."}, "title":{"label":"Outfit - Ellen Ford"}, "link":{"attributes":{"rel":"alternate", "type":"text/html", "href":"https://itunes.apple.com/us/podcast/outfit/id1382351003?mt=2&uo=2"}}, "id":{"label":"https://itunes.apple.com/us/podcast/outfit/id1382351003?mt=2&uo=2", "attributes":{"im:id":"1382351003"}}, "im:artist":{"label":"Ellen Ford"}, "category":{"attributes":{"im:id":"1459", "term":"Fashion & Beauty", "scheme":"https://itunes.apple.com/us/genre/podcasts-arts-fashion-beauty/id1459?mt=2&uo=2", "label":"Fashion & Beauty"}}, "im:releaseDate":{"label":"2018-05-08T10:47:00-07:00", "attributes":{"label":"May 8, 2018"}}}, 
{"im:name":{"label":"Natch Beaut"}, "im:price":{"label":"Get", "attributes":{"amount":"0", "currency":"USD"}}, "im:image":[
{"label":"https://is1-ssl.mzstatic.com/image/thumb/Podcasts118/v4/a6/7d/f1/a67df174-7344-9752-42b2-c77be9d81656/mza_8319914341127291934.jpg/55x55bb-85.png", "attributes":{"height":"55"}}, 
{"label":"https://is2-ssl.mzstatic.com/image/thumb/Podcasts118/v4/a6/7d/f1/a67df174-7344-9752-42b2-c77be9d81656/mza_8319914341127291934.jpg/60x60bb-85.png", "attributes":{"height":"60"}}, 
{"label":"https://is3-ssl.mzstatic.com/image/thumb/Podcasts118/v4/a6/7d/f1/a67df174-7344-9752-42b2-c77be9d81656/mza_8319914341127291934.jpg/170x170bb-85.png", "attributes":{"height":"170"}}], "summary":{"label":"Comedian and self-proclaimed \"beauty passionista\" Jackie Johnson loves being cute while living cruelty-free. Join her as she attempts to take the seriousness, mysteries, and intimidation out of makeup and skincare as she gabs with friends, artists, and indie entrepreneurs about what beauty and self-care means to them."}, "im:artist":{"label":"Jackie Johnson", "attributes":{"href":"https://itunes.apple.com/us/artist/starburns-audio/541109260?mt=2&uo=2"}}, "title":{"label":"Natch Beaut - Jackie Johnson"}, "link":{"attributes":{"rel":"alternate", "type":"text/html", "href":"https://itunes.apple.com/us/podcast/natch-beaut/id1223715132?mt=2&uo=2"}}, "id":{"label":"https://itunes.apple.com/us/podcast/natch-beaut/id1223715132?mt=2&uo=2", "attributes":{"im:id":"1223715132"}}, "im:contentType":{"attributes":{"term":"Podcast", "label":"Podcast"}}, "category":{"attributes":{"im:id":"1459", "term":"Fashion & Beauty", "scheme":"https://itunes.apple.com/us/genre/podcasts-arts-fashion-beauty/id1459?mt=2&uo=2", "label":"Fashion & Beauty"}}, "im:releaseDate":{"label":"2018-06-15T09:38:00-07:00", "attributes":{"label":"June 15, 2018"}}}, 
{"im:name":{"label":"The Beauty Brains"}, "im:price":{"label":"Get", "attributes":{"amount":"0", "currency":"USD"}}, "im:image":[
{"label":"https://is2-ssl.mzstatic.com/image/thumb/Podcasts71/v4/b2/a9/6f/b2a96f2e-83f4-5e4d-e8d4-da2084f38017/mza_1110652417917360699.jpg/55x55bb-85.png", "attributes":{"height":"55"}}, 
{"label":"https://is3-ssl.mzstatic.com/image/thumb/Podcasts71/v4/b2/a9/6f/b2a96f2e-83f4-5e4d-e8d4-da2084f38017/mza_1110652417917360699.jpg/60x60bb-85.png", "attributes":{"height":"60"}}, 
{"label":"https://is1-ssl.mzstatic.com/image/thumb/Podcasts71/v4/b2/a9/6f/b2a96f2e-83f4-5e4d-e8d4-da2084f38017/mza_1110652417917360699.jpg/170x170bb-85.png", "attributes":{"height":"170"}}], "summary":{"label":"We're cosmetic scientists who answer your beauty questions. We explain what the chemicals used in cosmetics really do, how products are tested, and what all the advertising really means. Listen to us and you'll be a smarter beauty consumer!"}, "im:artist":{"label":"Discover the beauty and cosmetic products you should use and avoid"}, "title":{"label":"The Beauty Brains - Discover the beauty and cosmetic products you should use and avoid"}, "link":{"attributes":{"rel":"alternate", "type":"text/html", "href":"https://itunes.apple.com/us/podcast/the-beauty-brains/id733300242?mt=2&uo=2"}}, "id":{"label":"https://itunes.apple.com/us/podcast/the-beauty-brains/id733300242?mt=2&uo=2", "attributes":{"im:id":"733300242"}}, "im:contentType":{"attributes":{"term":"Podcast", "label":"Podcast"}}, "category":{"attributes":{"im:id":"1459", "term":"Fashion & Beauty", "scheme":"https://itunes.apple.com/us/genre/podcasts-arts-fashion-beauty/id1459?mt=2&uo=2", "label":"Fashion & Beauty"}}, "im:releaseDate":{"label":"2018-01-18T12:22:00-07:00", "attributes":{"label":"January 18, 2018"}}}, 
{"im:name":{"label":"Velvet’s Edge"}, "im:image":[
{"label":"https://is2-ssl.mzstatic.com/image/thumb/Podcasts118/v4/7d/4a/ce/7d4ace23-c4da-7953-c1ba-48cc818cb4f2/mza_5196492066113583605.jpeg/55x55bb-85.png", "attributes":{"height":"55"}}, 
{"label":"https://is3-ssl.mzstatic.com/image/thumb/Podcasts118/v4/7d/4a/ce/7d4ace23-c4da-7953-c1ba-48cc818cb4f2/mza_5196492066113583605.jpeg/60x60bb-85.png", "attributes":{"height":"60"}}, 
{"label":"https://is5-ssl.mzstatic.com/image/thumb/Podcasts118/v4/7d/4a/ce/7d4ace23-c4da-7953-c1ba-48cc818cb4f2/mza_5196492066113583605.jpeg/170x170bb-85.png", "attributes":{"height":"170"}}], "summary":{"label":"Based on the lifestyle blog Velvetsedge.com. This podcast will answer lifestyle questions from beauty and fashion to travel and health.\nFeaturing interviews with interesting people from the life of one of Nashville's most prominent female tastemakers and tastefinders. "}, "im:price":{"label":"Get", "attributes":{"amount":"0", "currency":"USD"}}, "im:contentType":{"attributes":{"term":"Podcast", "label":"Podcast"}}, "rights":{"label":"© Nashville Podcast Network"}, "title":{"label":"Velvet’s Edge - Nashville Podcast Network"}, "link":{"attributes":{"rel":"alternate", "type":"text/html", "href":"https://itunes.apple.com/us/podcast/velvets-edge/id1364128350?mt=2&uo=2"}}, "id":{"label":"https://itunes.apple.com/us/podcast/velvets-edge/id1364128350?mt=2&uo=2", "attributes":{"im:id":"1364128350"}}, "im:artist":{"label":"Nashville Podcast Network"}, "category":{"attributes":{"im:id":"1459", "term":"Fashion & Beauty", "scheme":"https://itunes.apple.com/us/genre/podcasts-arts-fashion-beauty/id1459?mt=2&uo=2", "label":"Fashion & Beauty"}}, "im:releaseDate":{"label":"2018-06-12T22:01:00-07:00", "attributes":{"label":"June 12, 2018"}}}, 
{"im:name":{"label":"The Beauty Biz Show | For Beauty Industry Experts & Practitioners, Estheticians, Hair Stylists, Massage Therapists & Nail Tec"}, "im:image":[
{"label":"https://is4-ssl.mzstatic.com/image/thumb/Podcasts62/v4/28/e7/d5/28e7d5cd-f6e3-7b39-53b3-f3ae263dafa7/mza_8984695619963562560.jpg/55x55bb-85.png", "attributes":{"height":"55"}}, 
{"label":"https://is5-ssl.mzstatic.com/image/thumb/Podcasts62/v4/28/e7/d5/28e7d5cd-f6e3-7b39-53b3-f3ae263dafa7/mza_8984695619963562560.jpg/60x60bb-85.png", "attributes":{"height":"60"}}, 
{"label":"https://is5-ssl.mzstatic.com/image/thumb/Podcasts62/v4/28/e7/d5/28e7d5cd-f6e3-7b39-53b3-f3ae263dafa7/mza_8984695619963562560.jpg/170x170bb-85.png", "attributes":{"height":"170"}}], "summary":{"label":"Hosted by celebrity esthetician & industry expert Lori Crete, each Beauty Biz Show episode is designed to help you tap into your best success and leave you feeling inspired to build the beauty biz of your dreams! Featuring industry icons and gurus, revenue-driving tips and motivational messages, Lori and her guests inspire you to burst through stagnant industry norms to flourish in your profession and make a beautiful, abundant living doing what you love.\nA finalist for American Spa Magazine’s 2017 Women in Wellness Mentor of the Year, Lori is a highly sought after industry expert and licensed celebrity esthetician. Owner of Southern California’s Spa 10, she is also the founder of The Beauty Biz Club™, a success-based society dedicated to helping beauty practitioners around the world fill their schedule, increase profits and break through to the 6-figure mark. For more about Lori & the Beauty Biz Club, visit https://beautybizclub.com."}, "im:price":{"label":"Get", "attributes":{"amount":"0", "currency":"USD"}}, "im:contentType":{"attributes":{"term":"Podcast", "label":"Podcast"}}, "rights":{"label":"© 2018 The Esthetician Mentor"}, "title":{"label":"The Beauty Biz Show | For Beauty Industry Experts & Practitioners, Estheticians, Hair Stylists, Massage Therapists & Nail Tec - Lori Crete | The Beauty Biz Club"}, "link":{"attributes":{"rel":"alternate", "type":"text/html", "href":"https://itunes.apple.com/us/podcast/beauty-biz-show-for-beauty-industry-experts-practitioners/id980461189?mt=2&uo=2"}}, "id":{"label":"https://itunes.apple.com/us/podcast/beauty-biz-show-for-beauty-industry-experts-practitioners/id980461189?mt=2&uo=2", "attributes":{"im:id":"980461189"}}, "im:artist":{"label":"Lori Crete | The Beauty Biz Club"}, "category":{"attributes":{"im:id":"1459", "term":"Fashion & Beauty", "scheme":"https://itunes.apple.com/us/genre/podcasts-arts-fashion-beauty/id1459?mt=2&uo=2", "label":"Fashion & Beauty"}}, "im:releaseDate":{"label":"2018-06-10T19:00:00-07:00", "attributes":{"label":"June 10, 2018"}}}, 
{"im:name":{"label":"The Emma Guns Show"}, "im:price":{"label":"Get", "attributes":{"amount":"0", "currency":"USD"}}, "im:image":[
{"label":"https://is2-ssl.mzstatic.com/image/thumb/Podcasts115/v4/37/6d/59/376d5949-15a5-cba5-f440-72fd92576fe4/mza_8263694800338365310.jpg/55x55bb-85.png", "attributes":{"height":"55"}}, 
{"label":"https://is3-ssl.mzstatic.com/image/thumb/Podcasts115/v4/37/6d/59/376d5949-15a5-cba5-f440-72fd92576fe4/mza_8263694800338365310.jpg/60x60bb-85.png", "attributes":{"height":"60"}}, 
{"label":"https://is5-ssl.mzstatic.com/image/thumb/Podcasts115/v4/37/6d/59/376d5949-15a5-cba5-f440-72fd92576fe4/mza_8263694800338365310.jpg/170x170bb-85.png", "attributes":{"height":"170"}}], "summary":{"label":"On The Emma Guns Show, journalist and broadcaster Emma Gunavardhana gets deep and meaningful with experts from the health, wellness and beauty fields. In each episode you'll hear in-depth conversations with everyone from Pixiwoo's Sam and Nic, Michelle Visage, Gretchen Rubin, Iskra Lawrence and Elizabeth Hurley. It's a relaxed hour of chat that's not afraid to tackle complex topics such as mental health, depression and anxiety or unpick the failures, challenges and set-backs that ultimately steered guests towards success. Each show is designed to leave you feeling entertained, informed and inspired."}, "im:artist":{"label":"Emma Gunavardhana"}, "title":{"label":"The Emma Guns Show - Emma Gunavardhana"}, "link":{"attributes":{"rel":"alternate", "type":"text/html", "href":"https://itunes.apple.com/us/podcast/the-emma-guns-show/id1102982843?mt=2&uo=2"}}, "id":{"label":"https://itunes.apple.com/us/podcast/the-emma-guns-show/id1102982843?mt=2&uo=2", "attributes":{"im:id":"1102982843"}}, "im:contentType":{"attributes":{"term":"Podcast", "label":"Podcast"}}, "category":{"attributes":{"im:id":"1459", "term":"Fashion & Beauty", "scheme":"https://itunes.apple.com/us/genre/podcasts-arts-fashion-beauty/id1459?mt=2&uo=2", "label":"Fashion & Beauty"}}, "im:releaseDate":{"label":"2018-06-17T16:01:00-07:00", "attributes":{"label":"June 17, 2018"}}}, 
{"im:name":{"label":"At Home With..."}, "im:image":[
{"label":"https://is4-ssl.mzstatic.com/image/thumb/Podcasts115/v4/77/07/58/770758b8-fa56-467b-adf8-900dde07163c/mza_2038074522688177176.jpg/55x55bb-85.png", "attributes":{"height":"55"}}, 
{"label":"https://is5-ssl.mzstatic.com/image/thumb/Podcasts115/v4/77/07/58/770758b8-fa56-467b-adf8-900dde07163c/mza_2038074522688177176.jpg/60x60bb-85.png", "attributes":{"height":"60"}}, 
{"label":"https://is1-ssl.mzstatic.com/image/thumb/Podcasts115/v4/77/07/58/770758b8-fa56-467b-adf8-900dde07163c/mza_2038074522688177176.jpg/170x170bb-85.png", "attributes":{"height":"170"}}], "summary":{"label":"Your home says so much about you - where you’ve travelled, who you’ve met, and the kind of person you are. We’re Lily and Anna, lifestyle content creators. We’ve asked people we admire to open their front doors and talk about their lives, by taking a tour of their homes to discover who they really are. We’ve riffled through their wardrobes, nosed through their fridges and even scrolled through their Sky+ recordings, to shed some light on their fascinating lives. Join us At Home With…"}, "im:price":{"label":"Get", "attributes":{"amount":"0", "currency":"USD"}}, "im:contentType":{"attributes":{"term":"Podcast", "label":"Podcast"}}, "rights":{"label":"© Lily Pebbles and Anna Newton. All rights reserved."}, "title":{"label":"At Home With... - Lily Pebbles & Anna Newton"}, "link":{"attributes":{"rel":"alternate", "type":"text/html", "href":"https://itunes.apple.com/us/podcast/at-home-with/id1228706016?mt=2&uo=2"}}, "id":{"label":"https://itunes.apple.com/us/podcast/at-home-with/id1228706016?mt=2&uo=2", "attributes":{"im:id":"1228706016"}}, "im:artist":{"label":"Lily Pebbles & Anna Newton", "attributes":{"href":"https://itunes.apple.com/us/artist/gleam-futures/1199475672?mt=2&uo=2"}}, "category":{"attributes":{"im:id":"1459", "term":"Fashion & Beauty", "scheme":"https://itunes.apple.com/us/genre/podcasts-arts-fashion-beauty/id1459?mt=2&uo=2", "label":"Fashion & Beauty"}}, "im:releaseDate":{"label":"2017-07-11T22:00:00-07:00", "attributes":{"label":"July 11, 2017"}}}, 
{"im:name":{"label":"The Style Success Podcast"}, "im:image":[
{"label":"https://is5-ssl.mzstatic.com/image/thumb/Podcasts117/v4/e4/59/61/e45961a0-6fa0-88ce-00d5-e1c16c2794fb/mza_3768556744990653487.png/55x55bb-85.png", "attributes":{"height":"55"}}, 
{"label":"https://is1-ssl.mzstatic.com/image/thumb/Podcasts117/v4/e4/59/61/e45961a0-6fa0-88ce-00d5-e1c16c2794fb/mza_3768556744990653487.png/60x60bb-85.png", "attributes":{"height":"60"}}, 
{"label":"https://is2-ssl.mzstatic.com/image/thumb/Podcasts117/v4/e4/59/61/e45961a0-6fa0-88ce-00d5-e1c16c2794fb/mza_3768556744990653487.png/170x170bb-85.png", "attributes":{"height":"170"}}], "summary":{"label":"The Style Success Podcast is a show hosted by Image & Wardrobe Consultant, Mallory Sills.  Helping women increase confidence, credibility and developing their own personal style is Mallory's mission.  Tune in to learn Mallory's unique insight on the style and beauty world as she shares her knowledge and passion. Come join the style success movement!"}, "im:price":{"label":"Get", "attributes":{"amount":"0", "currency":"USD"}}, "im:contentType":{"attributes":{"term":"Podcast", "label":"Podcast"}}, "rights":{"label":"© All content and information shared is property of Image Success by Mallory, Ltd."}, "title":{"label":"The Style Success Podcast - Mallory Sills, Image Consultant, Style Tips, Personal Stylist, Personal Branding, Wardrobe Consultant, Style Help, Self Help, Business, Style, Fashion & Beauty"}, "link":{"attributes":{"rel":"alternate", "type":"text/html", "href":"https://itunes.apple.com/us/podcast/the-style-success-podcast/id963972595?mt=2&uo=2"}}, "id":{"label":"https://itunes.apple.com/us/podcast/the-style-success-podcast/id963972595?mt=2&uo=2", "attributes":{"im:id":"963972595"}}, "im:artist":{"label":"Mallory Sills, Image Consultant, Style Tips, Personal Stylist, Personal Branding, Wardrobe Consultant, Style Help, Self Help, Business, Style, Fashion & Beauty"}, "category":{"attributes":{"im:id":"1459", "term":"Fashion & Beauty", "scheme":"https://itunes.apple.com/us/genre/podcasts-arts-fashion-beauty/id1459?mt=2&uo=2", "label":"Fashion & Beauty"}}, "im:releaseDate":{"label":"2018-06-15T13:25:00-07:00", "attributes":{"label":"June 15, 2018"}}}, 
{"im:name":{"label":"the mustards"}, "im:price":{"label":"Get", "attributes":{"amount":"0", "currency":"USD"}}, "im:image":[
{"label":"https://is1-ssl.mzstatic.com/image/thumb/Podcasts115/v4/bf/3b/9a/bf3b9a51-6ef8-43d4-f1a2-8b27286e340a/mza_3126496399352243400.jpg/55x55bb-85.png", "attributes":{"height":"55"}}, 
{"label":"https://is2-ssl.mzstatic.com/image/thumb/Podcasts115/v4/bf/3b/9a/bf3b9a51-6ef8-43d4-f1a2-8b27286e340a/mza_3126496399352243400.jpg/60x60bb-85.png", "attributes":{"height":"60"}}, 
{"label":"https://is2-ssl.mzstatic.com/image/thumb/Podcasts115/v4/bf/3b/9a/bf3b9a51-6ef8-43d4-f1a2-8b27286e340a/mza_3126496399352243400.jpg/170x170bb-85.png", "attributes":{"height":"170"}}], "summary":{"label":"a podcast about everything that 'the mustards' aka jenny and david find interesting. minimalism, travel, love, food, health, interior design, movies, politics, fashion - and everything hygge of course !"}, "im:artist":{"label":"jenny mustard"}, "title":{"label":"the mustards - jenny mustard"}, "link":{"attributes":{"rel":"alternate", "type":"text/html", "href":"https://itunes.apple.com/us/podcast/the-mustards/id1193988503?mt=2&uo=2"}}, "id":{"label":"https://itunes.apple.com/us/podcast/the-mustards/id1193988503?mt=2&uo=2", "attributes":{"im:id":"1193988503"}}, "im:contentType":{"attributes":{"term":"Podcast", "label":"Podcast"}}, "category":{"attributes":{"im:id":"1459", "term":"Fashion & Beauty", "scheme":"https://itunes.apple.com/us/genre/podcasts-arts-fashion-beauty/id1459?mt=2&uo=2", "label":"Fashion & Beauty"}}, "im:releaseDate":{"label":"2018-06-17T22:00:00-07:00", "attributes":{"label":"June 17, 2018"}}}, 
{"im:name":{"label":"Tom & Lorenzo's Pop Style Opinionfest"}, "im:image":[
{"label":"https://is3-ssl.mzstatic.com/image/thumb/Podcasts128/v4/3d/41/44/3d41448d-4d98-dc94-0cdc-c56fc3b16d41/mza_768851048151581919.jpg/55x55bb-85.png", "attributes":{"height":"55"}}, 
{"label":"https://is4-ssl.mzstatic.com/image/thumb/Podcasts128/v4/3d/41/44/3d41448d-4d98-dc94-0cdc-c56fc3b16d41/mza_768851048151581919.jpg/60x60bb-85.png", "attributes":{"height":"60"}}, 
{"label":"https://is4-ssl.mzstatic.com/image/thumb/Podcasts128/v4/3d/41/44/3d41448d-4d98-dc94-0cdc-c56fc3b16d41/mza_768851048151581919.jpg/170x170bb-85.png", "attributes":{"height":"170"}}], "summary":{"label":"Authors and bloggers Tom Fitzgerald and Lorenzo Marquez render judgment on all the latest goings-on in the worlds of celebrity, pop culture, television and fashion. Strap yourselves in for some hilarious opinionating on all the most pressing issues of our time, darlings."}, "im:price":{"label":"Get", "attributes":{"amount":"0", "currency":"USD"}}, "im:contentType":{"attributes":{"term":"Podcast", "label":"Podcast"}}, "rights":{"label":"© 2018 Radio.com"}, "title":{"label":"Tom & Lorenzo's Pop Style Opinionfest - Radio.com"}, "link":{"attributes":{"rel":"alternate", "type":"text/html", "href":"https://itunes.apple.com/us/podcast/tom-lorenzos-pop-style-opinionfest/id980669909?mt=2&uo=2"}}, "id":{"label":"https://itunes.apple.com/us/podcast/tom-lorenzos-pop-style-opinionfest/id980669909?mt=2&uo=2", "attributes":{"im:id":"980669909"}}, "im:artist":{"label":"Radio.com", "attributes":{"href":"https://itunes.apple.com/us/artist/radio-com/1343886161?mt=2&uo=2"}}, "category":{"attributes":{"im:id":"1459", "term":"Fashion & Beauty", "scheme":"https://itunes.apple.com/us/genre/podcasts-arts-fashion-beauty/id1459?mt=2&uo=2", "label":"Fashion & Beauty"}}, "im:releaseDate":{"label":"2018-06-15T14:17:00-07:00", "attributes":{"label":"June 15, 2018"}}}, 
{"im:name":{"label":"A Few Things with Claire and Erica"}, "im:image":[
{"label":"https://is4-ssl.mzstatic.com/image/thumb/Podcasts118/v4/a2/7d/ba/a27dbad0-ba0e-ae77-ccfb-9999e38d833c/mza_2992193812897109005.jpeg/55x55bb-85.png", "attributes":{"height":"55"}}, 
{"label":"https://is5-ssl.mzstatic.com/image/thumb/Podcasts118/v4/a2/7d/ba/a27dbad0-ba0e-ae77-ccfb-9999e38d833c/mza_2992193812897109005.jpeg/60x60bb-85.png", "attributes":{"height":"60"}}, 
{"label":"https://is1-ssl.mzstatic.com/image/thumb/Podcasts118/v4/a2/7d/ba/a27dbad0-ba0e-ae77-ccfb-9999e38d833c/mza_2992193812897109005.jpeg/170x170bb-85.png", "attributes":{"height":"170"}}], "summary":{"label":"Hosts Claire Mazur and Erica Cerulo, co-founders of the emerging design site Of a Kind, expand upon the theme of their highly popular “10 Things” newsletter to share their latest and greatest discoveries. Each episode drills down into the nitty-gritty of two to four finds—covering topics across food, beauty, technology, literature, you name it—and often features a guest who has insider intel to contribute."}, "im:price":{"label":"Get", "attributes":{"amount":"0", "currency":"USD"}}, "im:contentType":{"attributes":{"term":"Podcast", "label":"Podcast"}}, "rights":{"label":"© Of a Kind"}, "title":{"label":"A Few Things with Claire and Erica - Of a Kind"}, "link":{"attributes":{"rel":"alternate", "type":"text/html", "href":"https://itunes.apple.com/us/podcast/a-few-things-with-claire-and-erica/id993666762?mt=2&uo=2"}}, "id":{"label":"https://itunes.apple.com/us/podcast/a-few-things-with-claire-and-erica/id993666762?mt=2&uo=2", "attributes":{"im:id":"993666762"}}, "im:artist":{"label":"Of a Kind", "attributes":{"href":"https://itunes.apple.com/us/artist/heritage-radio-network/525222017?mt=2&uo=2"}}, "category":{"attributes":{"im:id":"1459", "term":"Fashion & Beauty", "scheme":"https://itunes.apple.com/us/genre/podcasts-arts-fashion-beauty/id1459?mt=2&uo=2", "label":"Fashion & Beauty"}}, "im:releaseDate":{"label":"2018-06-18T08:04:00-07:00", "attributes":{"label":"June 18, 2018"}}}, 
{"im:name":{"label":"Fashion Is Your Business - a retail technology podcast"}, "im:image":[
{"label":"https://is5-ssl.mzstatic.com/image/thumb/Podcasts62/v4/e1/9a/81/e19a81cd-bb44-2529-5ded-f7b345f55673/mza_7963670054860990534.png/55x55bb-85.png", "attributes":{"height":"55"}}, 
{"label":"https://is1-ssl.mzstatic.com/image/thumb/Podcasts62/v4/e1/9a/81/e19a81cd-bb44-2529-5ded-f7b345f55673/mza_7963670054860990534.png/60x60bb-85.png", "attributes":{"height":"60"}}, 
{"label":"https://is4-ssl.mzstatic.com/image/thumb/Podcasts62/v4/e1/9a/81/e19a81cd-bb44-2529-5ded-f7b345f55673/mza_7963670054860990534.png/170x170bb-85.png", "attributes":{"height":"170"}}], "summary":{"label":"Fashion Is Your Business is a weekly show about FASHIONTECH, the intersection of fashion business and fashion technology. The podcast is produced through MouthMedia Network. The hosts are entrepreneurial strategist Rob Sanchez, leading fashion technology consultant Pavan Bahl, and creative entrepreneur Marc Raco. Guests include the world's foremost fashion technology pioneers, discussing textiles to retail and everything in between, it covers business news from startups to conglomerates, and the show has a fun and accessible morning radio vibe."}, "im:price":{"label":"Get", "attributes":{"amount":"0", "currency":"USD"}}, "im:contentType":{"attributes":{"term":"Podcast", "label":"Podcast"}}, "rights":{"label":"© MouthMedia Network"}, "title":{"label":"Fashion Is Your Business - a retail technology podcast - MouthMedia Network"}, "link":{"attributes":{"rel":"alternate", "type":"text/html", "href":"https://itunes.apple.com/us/podcast/fashion-is-your-business-a-retail-technology-podcast/id954158712?mt=2&uo=2"}}, "id":{"label":"https://itunes.apple.com/us/podcast/fashion-is-your-business-a-retail-technology-podcast/id954158712?mt=2&uo=2", "attributes":{"im:id":"954158712"}}, "im:artist":{"label":"MouthMedia Network", "attributes":{"href":"https://itunes.apple.com/us/artist/mouthmedia-network/1084795832?mt=2&uo=2"}}, "category":{"attributes":{"im:id":"1459", "term":"Fashion & Beauty", "scheme":"https://itunes.apple.com/us/genre/podcasts-arts-fashion-beauty/id1459?mt=2&uo=2", "label":"Fashion & Beauty"}}, "im:releaseDate":{"label":"2018-06-12T07:30:00-07:00", "attributes":{"label":"June 12, 2018"}}}, 
{"im:name":{"label":"#LIPSTORIES"}, "im:image":[
{"label":"https://is1-ssl.mzstatic.com/image/thumb/Podcasts118/v4/70/51/50/70515052-9dd1-e13d-04e6-e7dcb750b22b/mza_5979283209788736791.jpg/55x55bb-85.png", "attributes":{"height":"55"}}, 
{"label":"https://is2-ssl.mzstatic.com/image/thumb/Podcasts118/v4/70/51/50/70515052-9dd1-e13d-04e6-e7dcb750b22b/mza_5979283209788736791.jpg/60x60bb-85.png", "attributes":{"height":"60"}}, 
{"label":"https://is1-ssl.mzstatic.com/image/thumb/Podcasts118/v4/70/51/50/70515052-9dd1-e13d-04e6-e7dcb750b22b/mza_5979283209788736791.jpg/170x170bb-85.png", "attributes":{"height":"170"}}], "summary":{"label":"On each episode of #LIPSTORIES influential female founders, creators and thought leaders take listeners through some of their most notable, inspiring, funny stories from their everyday lives—while they’re out traveling the world, crushing it at work, or even just hanging out with friends. Presented by Girlboss Radio in partnership with Sephora Collection."}, "im:price":{"label":"Get", "attributes":{"amount":"0", "currency":"USD"}}, "im:contentType":{"attributes":{"term":"Podcast", "label":"Podcast"}}, "rights":{"label":"© 2018 Girlboss Media. All Rights Reserved."}, "title":{"label":"#LIPSTORIES - Girlboss Media"}, "link":{"attributes":{"rel":"alternate", "type":"text/html", "href":"https://itunes.apple.com/us/podcast/lipstories/id1370728732?mt=2&uo=2"}}, "id":{"label":"https://itunes.apple.com/us/podcast/lipstories/id1370728732?mt=2&uo=2", "attributes":{"im:id":"1370728732"}}, "im:artist":{"label":"Girlboss Media"}, "category":{"attributes":{"im:id":"1459", "term":"Fashion & Beauty", "scheme":"https://itunes.apple.com/us/genre/podcasts-arts-fashion-beauty/id1459?mt=2&uo=2", "label":"Fashion & Beauty"}}, "im:releaseDate":{"label":"2018-04-26T00:00:00-07:00", "attributes":{"label":"April 26, 2018"}}}, 
{"im:name":{"label":"The Hair Game"}, "im:image":[
{"label":"https://is1-ssl.mzstatic.com/image/thumb/Podcasts118/v4/bc/e6/35/bce6351b-ea11-f358-b544-9e10bf23f487/mza_573904074995810233.jpeg/55x55bb-85.png", "attributes":{"height":"55"}}, 
{"label":"https://is2-ssl.mzstatic.com/image/thumb/Podcasts118/v4/bc/e6/35/bce6351b-ea11-f358-b544-9e10bf23f487/mza_573904074995810233.jpeg/60x60bb-85.png", "attributes":{"height":"60"}}, 
{"label":"https://is5-ssl.mzstatic.com/image/thumb/Podcasts118/v4/bc/e6/35/bce6351b-ea11-f358-b544-9e10bf23f487/mza_573904074995810233.jpeg/170x170bb-85.png", "attributes":{"height":"170"}}], "summary":{"label":"The Hair Game is a series brought to you by Salon Republic and hosted by founder Eric Taylor, who, after 17 yrs in the hair game, has seen a lot of s#!@ go down. We'll go deep with the beauty industry's most interesting players, we'll educate and tell stories about the things you care about, we'll get into the business side of the game so you can earn more and keep more, and we'll go #BTS to show you how we do things at Salon Republic. Also check out the video content on salonrepublic.com/thehairgame ."}, "im:price":{"label":"Get", "attributes":{"amount":"0", "currency":"USD"}}, "im:contentType":{"attributes":{"term":"Podcast", "label":"Podcast"}}, "rights":{"label":"© All rights reserved by Salon Republic LLC"}, "title":{"label":"The Hair Game - Salon Republic"}, "link":{"attributes":{"rel":"alternate", "type":"text/html", "href":"https://itunes.apple.com/us/podcast/the-hair-game/id1266398652?mt=2&uo=2"}}, "id":{"label":"https://itunes.apple.com/us/podcast/the-hair-game/id1266398652?mt=2&uo=2", "attributes":{"im:id":"1266398652"}}, "im:artist":{"label":"Salon Republic"}, "category":{"attributes":{"im:id":"1459", "term":"Fashion & Beauty", "scheme":"https://itunes.apple.com/us/genre/podcasts-arts-fashion-beauty/id1459?mt=2&uo=2", "label":"Fashion & Beauty"}}, "im:releaseDate":{"label":"2018-06-15T02:00:00-07:00", "attributes":{"label":"June 15, 2018"}}}, 
{"im:name":{"label":"AnxieTEA: Sex/Pop/Issues"}, "im:price":{"label":"Get", "attributes":{"amount":"0", "currency":"USD"}}, "im:image":[
{"label":"https://is4-ssl.mzstatic.com/image/thumb/Podcasts118/v4/bf/89/d6/bf89d6a4-d9ad-9e51-1dd0-a1a17350037e/mza_4850809507132638471.png/55x55bb-85.png", "attributes":{"height":"55"}}, 
{"label":"https://is5-ssl.mzstatic.com/image/thumb/Podcasts118/v4/bf/89/d6/bf89d6a4-d9ad-9e51-1dd0-a1a17350037e/mza_4850809507132638471.png/60x60bb-85.png", "attributes":{"height":"60"}}, 
{"label":"https://is5-ssl.mzstatic.com/image/thumb/Podcasts118/v4/bf/89/d6/bf89d6a4-d9ad-9e51-1dd0-a1a17350037e/mza_4850809507132638471.png/170x170bb-85.png", "attributes":{"height":"170"}}], "summary":{"label":"AnxieTEA: Sex, Pop, Issues and Advice with two gays just as lost as you!\n\nHost: Zara Barrie & Donny Meacham"}, "im:artist":{"label":"AnxieTEAradio"}, "title":{"label":"AnxieTEA: Sex/Pop/Issues - AnxieTEAradio"}, "link":{"attributes":{"rel":"alternate", "type":"text/html", "href":"https://itunes.apple.com/us/podcast/anxietea-sex-pop-issues/id1362761504?mt=2&uo=2"}}, "id":{"label":"https://itunes.apple.com/us/podcast/anxietea-sex-pop-issues/id1362761504?mt=2&uo=2", "attributes":{"im:id":"1362761504"}}, "im:contentType":{"attributes":{"term":"Podcast", "label":"Podcast"}}, "category":{"attributes":{"im:id":"1459", "term":"Fashion & Beauty", "scheme":"https://itunes.apple.com/us/genre/podcasts-arts-fashion-beauty/id1459?mt=2&uo=2", "label":"Fashion & Beauty"}}, "im:releaseDate":{"label":"2018-06-14T18:35:00-07:00", "attributes":{"label":"June 14, 2018"}}}], "updated":{"label":"2018-06-18T13:57:41-07:00"}, "rights":{"label":"Copyright 2008 Apple Inc."}, "title":{"label":"iTunes Store: Top Podcasts in Fashion & Beauty"}, "icon":{"label":"http://itunes.apple.com/favicon.ico"}, "link":[
{"attributes":{"rel":"alternate", "type":"text/html", "href":"https://itunes.apple.com/WebObjects/MZStore.woa/wa/viewTop?cc=us&id=20044&popId=3"}}, 
{"attributes":{"rel":"self", "href":"https://itunes.apple.com/us/rss/toppodcasts/genre=1459/limit=20/json"}}], "id":{"label":"https://itunes.apple.com/us/rss/toppodcasts/genre=1459/limit=20/json"}}}